easier_docker-2.2.7.dist-info/licenses/LICENSE
easierdocker/__init__.py
easierdocker/__main__.py
easierdocker/config.py
easierdocker/constants.py
easierdocker/docker_utils.py
easierdocker/easier_docker.py
easierdocker/easier_docker.pyi
easierdocker/exceptions.py
easierdocker/log_re.py
easierdocker/reload_process.py
easier_docker-2.2.7.dist-info/METADATA
easier_docker-2.2.7.dist-info/WHEEL
easier_docker-2.2.7.dist-info/entry_points.txt
easier_docker-2.2.7.dist-info/top_level.txt
easier_docker-2.2.7.dist-info/RECORD
