Metadata-Version: 2.4
Name: easier-docker
Version: 2.2.7
Summary: Configure your container image information more easily in python, allowing the container in docker to execute the configured program you want to execute.
Author-email: EnSong Wei <touer0018@gmail.com>
License: Apache License 2.0
Project-URL: Homepage, https://github.com/touero/easier-docker
Project-URL: Bug Reports, https://github.com/touero/easier-docker/issues
Project-URL: Source, https://github.com/touero/easier-docker
Keywords: easy,docker,python,docker sdk,python sdk
Classifier: License :: OSI Approved :: Apache Software License
Classifier: Programming Language :: Python :: 3.8
Classifier: Programming Language :: Python :: 3.9
Classifier: Programming Language :: Python :: 3.10
Classifier: Programming Language :: Python :: 3.11
Classifier: Programming Language :: Python :: 3.12
Classifier: Programming Language :: Python :: 3.13
Requires-Python: >=3.8
License-File: LICENSE
Requires-Dist: docker~=7.1.0
Requires-Dist: setuptools~=68.2.0
Requires-Dist: PyYAML~=6.0.1
Requires-Dist: wheel~=0.42.0
Requires-Dist: twine~=4.0.2
Requires-Dist: coverage==7.4.4
Dynamic: license-file
